novelai/__init__.py
novelai/__main__.py
novelai/exceptions.py
novelai/_api/__init__.py
novelai/_api/client.py
novelai/_client/__init__.py
novelai/_client/client.py
novelai/_utils/__init__.py
novelai/_utils/converter.py
novelai/_utils/image.py
novelai/_utils/nai_meta.py
novelai/constants/models.py
novelai/constants/negative_prompts.py
novelai/constants/noise_schedules.py
novelai/constants/positions.py
novelai/constants/samplers.py
novelai/constants/sizes.py
novelai/types/__init__.py
novelai/types/api/image.py
novelai/types/user/image.py
novelai/utils/metadata.py
novelai_sdk-0.4.3.dist-info/METADATA
novelai_sdk-0.4.3.dist-info/WHEEL
novelai_sdk-0.4.3.dist-info/licenses/LICENSE
novelai_sdk-0.4.3.dist-info/RECORD
