Metadata-Version: 2.4
Name: novelai-sdk
Version: 0.4.3
Summary: A Python SDK library for the NovelAI API with validation powered by Pydantic
Project-URL: Homepage, https://github.com/caru-ini/novelai-sdk
Project-URL: Repository, https://github.com/caru-ini/novelai-sdk
Project-URL: Issues, https://github.com/caru-ini/novelai-sdk/issues
Project-URL: Documentation, https://github.com/caru-ini/novelai-sdk#readme
Author-email: caru-ini <caru17122@gmail.com>
License: MIT
License-File: LICENSE
Keywords: ai,api,image-generation,novelai,pydantic,stable-diffusion
Classifier: Development Status :: 3 - Alpha
Classifier: Intended Audience :: Developers
Classifier: License :: OSI Approved :: MIT License
Classifier: Programming Language :: Python :: 3
Classifier: Programming Language :: Python :: 3.10
Classifier: Programming Language :: Python :: 3.11
Classifier: Programming Language :: Python :: 3.12
Classifier: Programming Language :: Python :: 3.13
Classifier: Topic :: Multimedia :: Graphics
Classifier: Topic :: Software Development :: Libraries :: Python Modules
Classifier: Typing :: Typed
Requires-Python: >=3.10
Requires-Dist: httpx>=0.28.1
Requires-Dist: numpy>=2.2.6
Requires-Dist: pillow>=12.0.0
Requires-Dist: pydantic>=2.12.3
Requires-Dist: python-dotenv>=1.1.1
Provides-Extra: build
Requires-Dist: uv>=0.6.14; extra == 'build'
